flask_image_resizer/__init__.py
flask_image_resizer/core.py
flask_image_resizer/modes.py
flask_image_resizer/size.py
flask_image_resizer/transform.py
Flask_Image_Resizer-3.0.7.dist-info/AUTHORS.txt
Flask_Image_Resizer-3.0.7.dist-info/LICENSE.txt
Flask_Image_Resizer-3.0.7.dist-info/METADATA
Flask_Image_Resizer-3.0.7.dist-info/WHEEL
Flask_Image_Resizer-3.0.7.dist-info/top_level.txt
Flask_Image_Resizer-3.0.7.dist-info/RECORD
