Metadata-Version: 2.1
Name: Flask-Image-Resizer
Version: 3.0.7
Summary: Dynamic image resizing for Flask.
Home-page: http://github.com/mikeboers/Flask-Images
Author: Mike Boers
Author-email: flask_images@mikeboers.com
License: BSD-3
Classifier: Development Status :: 5 - Production/Stable
Classifier: Intended Audience :: Developers
Classifier: License :: OSI Approved :: BSD License
Classifier: Natural Language :: English
Classifier: Operating System :: OS Independent
Classifier: Programming Language :: Python :: 2
Classifier: Programming Language :: Python :: 3
Classifier: Topic :: Software Development :: Libraries :: Python Modules
License-File: LICENSE.txt
License-File: AUTHORS.txt
Requires-Dist: Flask >=2.2.4
Requires-Dist: itsdangerous >=2.1.2
Requires-Dist: Pillow >=9.1.0
Requires-Dist: six >=1.16.0
Requires-Dist: scour >=0.38.2
